tests/utils.py
tests/test_IOH_benchmarking.py
tests/test_IOH_function.py
tests/test_IOH_logger.py
tests/__init__.py
IOHexperimenter-0.2.9.2.dist-info/LICENSE.txt
IOHexperimenter-0.2.9.2.dist-info/METADATA
IOHexperimenter-0.2.9.2.dist-info/WHEEL
IOHexperimenter-0.2.9.2.dist-info/top_level.txt
IOHexperimenter-0.2.9.2.dist-info/RECORD
IOHexperimenter/IOH_benchmarking.py
IOHexperimenter/IOH_Utils.py
IOHexperimenter/IOHprofiler.py
IOHexperimenter/__init__.py
IOHexperimenter/IOH_logger.py
IOHexperimenter/IOH_function.py
IOHexperimenter/_IOHprofiler.cpython-38-x86_64-linux-gnu.so
