Metadata-Version: 2.1
Name: IOHexperimenter
Version: 0.2.9.2
Summary: The experimenter for Iterative Optimization Heuristic
Home-page: https://github.com/IOHprofiler/IOHexperimenter
Author: Furong Ye, Diederick Vermetten, and Hao Wang
Author-email: f.ye@liacs.leidenuniv.nl
License: UNKNOWN
Platform: UNKNOWN
Classifier: Programming Language :: Python :: 3
Classifier: License :: OSI Approved :: GNU General Public License v3 (GPLv3)
Requires-Python: >=3.6
Requires-Dist: numpy
